README.md
setup.py
xunionfind/UnionFind.py
xunionfind/__init__.py
xunionfind.egg-info/PKG-INFO
xunionfind.egg-info/SOURCES.txt
xunionfind.egg-info/dependency_links.txt
xunionfind.egg-info/top_level.txt