Metadata-Version: 1.0
Name: xunionfind
Version: 0.0.3
Summary: easy UnionFind model.
Home-page: https://github.com/XCLZ-STUDIO/xUnionFind
Author: W-Mai
Author-email: 1341398182@qq.com
License: MIT Licence
Platform: UNKNOWN
